gym_2048/__init__.py
gym_2048/env.py
gym_2048/game.py
gym_2048/is_possible.py
gym_2048/playground.py
gym_2048/test.py
gym_2048_extended-2.5.dist-info/LICENSE
gym_2048_extended-2.5.dist-info/METADATA
gym_2048_extended-2.5.dist-info/WHEEL
gym_2048_extended-2.5.dist-info/top_level.txt
gym_2048_extended-2.5.dist-info/RECORD
