Metadata-Version: 2.1
Name: gym-2048-extended
Version: 2.5
Summary: OpenAI Gym Environment for 2048 extended functionality
Home-page: https://www.github.com/geschnee/2048-gym
Author: Georg Schneeberger
License: MIT
License-File: LICENSE
Requires-Dist: numpy
Requires-Dist: pygame
Requires-Dist: gymnasium
